[{"id":0,"userId":19,"date":"Mon Jul 16 2000","start":"01:41:25","end":"10:03:51"},{"id":1,"userId":18,"date":"Tue Aug 16 2020","start":"03:19:50","end":"06:29:52"},{"id":2,"userId":19,"date":"Fri Aug 16 2020","start":"10:05:56","end":"01:06:34"},{"id":3,"userId":17,"date":"Fri Mar 16 2019","start":"06:17:51","end":"01:19:53"},{"id":4,"userId":17,"date":"Tue Aug 25 2015","start":"11:36:23","end":"10:18:32"},{"id":5,"userId":16,"date":"Fri Jul 15 2018","start":"02:47:47","end":"04:18:31"},{"id":6,"userId":15,"date":"Fri Mar 19 2019","start":"02:24:17","end":"02:36:28"},{"id":7,"userId":14,"date":"Tue Mar 9 2003","start":"07:55:54","end":"01:19:48"},{"id":8,"userId":14,"date":"Mon Mar 17 2016","start":"02:19:59","end":"03:10:50"},{"id":9,"userId":13,"date":"Fri Mar 16 2019","start":"10:50:18","end":"05:46:33"},{"id":10,"userId":13,"date":"Tue Jul 16 2000","start":"03:31:47","end":"08:02:21"},{"id":11,"userId":20,"date":"Mon Aug 18 2018","start":"11:34:36","end":"12:18:15"},{"id":12,"userId":13,"date":"Mon Aug 14 2002","start":"02:03:19","end":"04:53:44"},{"id":13,"userId":12,"date":"Fri Jul 16 2019","start":"10:47:44","end":"03:52:23"},{"id":14,"userId":12,"date":"Tue Aug 16 2020","start":"08:15:03","end":"12:52:06"},{"id":15,"userId":12,"date":"Tue Aug 25 2015","start":"08:42:23","end":"02:10:28"},{"id":16,"userId":11,"date":"Fri Jul 15 2018","start":"11:23:26","end":"05:59:52"},{"id":17,"userId":11,"date":"Tue Mar 16 2019","start":"03:48:15","end":"01:56:11"},{"id":18,"userId":10,"date":"Tue Jul 16 2000","start":"02:10:06","end":"08:41:04"},{"id":19,"userId":9,"date":"Tue Aug 25 2015","start":"08:03:43","end":"06:51:19"},{"id":20,"userId":20,"date":"Thu Oct 01 2020","start":"19:05:07","end":"19:05:09"},{"id":21,"userId":19,"date":"Thu Oct 01 2020","start":"19:11:46","end":"19:11:47"},{"id":22,"userId":20,"date":"Tue Oct 06 2020","start":"1:59:02","end":"1:59:04"},{"id":23,"userId":20,"date":"Wed Oct 07 2020","start":"17:18:50","end":"17:24:44"},{"id":24,"userId":20,"date":"Thu Oct 08 2020","start":"15:26:23"},{"id":25,"userId":20,"date":"Sat Oct 10 2020","start":"20:56:43","end":"20:56:44"},{"id":26,"userId":20,"date":"Sun Oct 11 2020","start":"11:15:32","end":"15:23:37"},{"id":27,"userId":19,"date":"Sun Oct 11 2020","start":"17:04:59","end":"17:05:09"},{"id":28,"userId":20,"date":"Mon Oct 12 2020","start":"1:07:21","end":"1:07:30"},{"id":29,"userId":19,"date":"Mon Oct 12 2020","start":"12:12:18","end":"12:12:19"},{"id":30,"userId":0,"date":"Mon Oct 12 2020","start":"12:13:47","end":"12:13:48"},{"id":31,"userId":1,"date":"Mon Oct 12 2020","start":"12:16:15","end":"12:16:16"},{"id":32,"userId":20,"date":"Tue Oct 13 2020","start":"11:30:12","end":"11:30:58"},{"id":33,"userId":19,"date":"Tue Oct 13 2020","start":"11:33:50","end":"11:33:51"},{"id":34,"userId":0,"date":"Tue Oct 13 2020","start":"15:15:30","end":"15:15:31"},{"id":35,"userId":1,"date":"Tue Oct 13 2020","start":"15:30:39","end":"15:30:41"},{"id":36,"userId":20,"date":"Wed Oct 14 2020","start":"14:32:05","end":"17:32:21"},{"id":37,"userId":20,"date":"Thu Oct 15 2020","start":"1:40:04","end":"1:40:09"},{"id":38,"userId":0,"date":"Thu Oct 15 2020","start":"1:41:58","end":"1:41:59"},{"id":39,"userId":19,"date":"Thu Oct 15 2020","start":"1:44:08","end":"1:44:14"},{"id":40,"userId":1,"date":"Thu Oct 15 2020","start":"2:00:34","end":"2:00:35"},{"id":41,"userId":9,"date":"Thu Oct 15 2020","start":"2:02:53","end":"2:02:54"},{"id":42,"userId":10,"date":"Thu Oct 15 2020","start":"2:09:57","end":"2:10:02"}]